LICENSE
forseti_lang/__init__.py
forseti_lang/__main__.py
forseti_lang/checkers/__init__.py
forseti_lang/checkers/all_.py
forseti_lang/checkers/staples.py
forseti_lang/checkers/staples_test.py
forseti_lang/checkers/syntax.py
forseti_lang/checkers/syntax_test.py
forseti_lang/exceptions.py
forseti_lang/execute.py
forseti_lang/execute_test.py
forseti_lang/functions/__init__.py
forseti_lang/functions/auto_execute.py
forseti_lang/functions/base.py
forseti_lang/functions/distance.py
forseti_lang/functions/distance_test.py
forseti_lang/functions/length.py
forseti_lang/functions/length_test.py
forseti_lang/functions/nearby.py
forseti_lang/functions/nearby_test.py
forseti_lang/functions/regex.py
forseti_lang/parse.py
forseti_lang/parse_test.py
forseti_lang-1.0.3.dist-info/LICENSE
forseti_lang-1.0.3.dist-info/METADATA
forseti_lang-1.0.3.dist-info/WHEEL
forseti_lang-1.0.3.dist-info/entry_points.txt
forseti_lang-1.0.3.dist-info/RECORD
