Metadata-Version: 2.1
Name: forseti-lang
Version: 1.0.3
Summary: The system for determining the compliance of the text with the specified rules
Home-page: https://github.com/Kirill-Lekhov/forseti_lang
License: MIT
Keywords: language_processing
Author: Kirill_Lekhov
Author-email: Kirill.Lekhov@mail.ru
Requires-Python: >=3.5,<4.0
Classifier: License :: OSI Approved :: MIT License
Classifier: Programming Language :: Python :: 3
Classifier: Programming Language :: Python :: 3.5
Classifier: Programming Language :: Python :: 3.6
Classifier: Programming Language :: Python :: 3.7
Classifier: Programming Language :: Python :: 3.8
Classifier: Programming Language :: Python :: 3.9
Classifier: Programming Language :: Python :: 3.10
Classifier: Programming Language :: Python :: 3.11
Project-URL: Repository, https://github.com/Kirill-Lekhov/forseti_lang
